{"traceEvents":[{"ph":"X","name":"OMPC Runtime Execution","pid":2736,"tid":2736,"ts":0.0,"dur":5216000.665,"args":{}},{"ph":"X","name":"Task 482","pid":2736,"tid":2739,"ts":43071.73099517822,"dur":571719.067,"args":{"mpi_tag":8,"target_region_index":0,"source_location":"unknown:0:0"},"cname":"yellow"},{"ph":"X","name":"Task 484","pid":2736,"tid":2739,"ts":614991.4580001831,"dur":604508.128,"args":{"mpi_tag":13,"target_region_index":0,"source_location":"unknown:0:0"},"cname":"yellow"},{"ph":"X","name":"Task 488","pid":2736,"tid":2739,"ts":1219721.236000061,"dur":598021.388,"args":{"mpi_tag":16,"target_region_index":0,"source_location":"unknown:0:0"},"cname":"yellow"},{"ph":"X","name":"Task 486","pid":2736,"tid":2739,"ts":1817963.5439987183,"dur":705954.411,"args":{"mpi_tag":7,"target_region_index":0,"source_location":"unknown:0:0"},"cname":"yellow"},{"ph":"X","name":"Task 483","pid":2736,"tid":2739,"ts":2524085.664993286,"dur":687974.141,"args":{"mpi_tag":21,"target_region_index":0,"source_location":"unknown:0:0"},"cname":"yellow"},{"ph":"X","name":"Task 485","pid":2736,"tid":2739,"ts":3212256.585998535,"dur":711515.691,"args":{"mpi_tag":25,"target_region_index":0,"source_location":"unknown:0:0"},"cname":"yellow"},{"ph":"X","name":"Task 489","pid":2736,"tid":2739,"ts":3924022.916999817,"dur":688369.54,"args":{"mpi_tag":29,"target_region_index":0,"source_location":"unknown:0:0"},"cname":"yellow"},{"ph":"X","name":"Task 487","pid":2736,"tid":2739,"ts":4612594.236999512,"dur":599563.248,"args":{"mpi_tag":32,"target_region_index":0,"source_location":"unknown:0:0"},"cname":"yellow"},{"ph":"M","name":"process_name","pid":2736,"args":{"name":"Worker Process 0"}},{"ph":"M","name":"process_sort_index","pid":2736,"args":{"sort_index":1}},{"ph":"M","name":"thread_name","pid":2736,"tid":2736,"args":{"name":"Gate Thread"}},{"ph":"M","name":"thread_sort_index","pid":2736,"tid":2736,"args":{"sort_index":32767}},{"ph":"M","name":"thread_name","pid":2736,"tid":2737,"args":{"name":"Heartbeat Thread"}},{"ph":"M","name":"thread_sort_index","pid":2736,"tid":2737,"args":{"sort_index":32768}},{"ph":"M","name":"thread_name","pid":2736,"tid":2738,"args":{"name":"Failure Handler Thread"}},{"ph":"M","name":"thread_sort_index","pid":2736,"tid":2738,"args":{"sort_index":32769}},{"ph":"M","name":"thread_name","pid":2736,"tid":2739,"args":{"name":"Execute Event Handler 0"}},{"ph":"M","name":"thread_sort_index","pid":2736,"tid":2739,"args":{"sort_index":32767}},{"ph":"M","name":"thread_name","pid":2736,"tid":2740,"args":{"name":"Data Event Handler 0"}},{"ph":"M","name":"thread_sort_index","pid":2736,"tid":2740,"args":{"sort_index":32767}},{"ph":"X","name":"OMPC Runtime Execution","pid":25110,"tid":25110,"ts":0.0,"dur":5215952.545,"args":{}},{"ph":"X","name":"unknown","pid":25110,"tid":25226,"ts":41528.371001197265,"dur":157.78000244140625,"args":{"source_location":"unknown:0:0"}},{"ph":"X","name":"unknown","pid":25110,"tid":25226,"ts":42200.92100424902,"dur":779.2400015258789,"args":{"source_location":"unknown:0:0"}},{"ph":"X","name":"unknown","pid":25110,"tid":25226,"ts":2525157.1450032727,"dur":157.61000213623046,"args":{"source_location":"unknown:0:0"}},{"ph":"X","name":"unknown","pid":25110,"tid":25231,"ts":40735.521002723144,"dur":619.0800033569336,"args":{"source_location":"unknown:0:0"}},{"ph":"X","name":"unknown","pid":25110,"tid":25231,"ts":41784.79099936621,"dur":303.11000091552734,"args":{"source_location":"unknown:0:0"}},{"ph":"X","name":"unknown","pid":25110,"tid":25231,"ts":1312733.949004127,"dur":99137.43300231933,"args":{"source_location":"unknown:0:0"}},{"ph":"X","name":"unknown","pid":25110,"tid":25231,"ts":1413471.7320012583,"dur":407.15000427246093,"args":{"source_location":"unknown:0:0"}},{"ph":"X","name":"unknown","pid":25110,"tid":25227,"ts":40622.72099967139,"dur":674.0400033569335,"args":{"source_location":"unknown:0:0"}},{"ph":"X","name":"unknown","pid":25110,"tid":25227,"ts":41375.641005469726,"dur":245.04999786376953,"args":{"source_location":"unknown:0:0"}},{"ph":"X","name":"unknown","pid":25110,"tid":25227,"ts":41707.261000586914,"dur":141.7100015258789,"args":{"source_location":"unknown:0:0"}},{"ph":"X","name":"unknown","pid":25110,"tid":25227,"ts":617149.3179997934,"dur":157.8000045776367,"args":{"source_location":"unknown:0:0"}},{"ph":"X","name":"unknown","pid":25110,"tid":25227,"ts":617391.6980046763,"dur":161.52999816894533,"args":{"source_location":"unknown:0:0"}},{"ph":"X","name":"unknown","pid":25110,"tid":25227,"ts":617640.3980016245,"dur":200.89000305175782,"args":{"source_location":"unknown:0:0"}},{"ph":"X","name":"unknown","pid":25110,"tid":25229,"ts":41967.15099997656,"dur":200.6699996948242,"args":{"source_location":"unknown:0:0"}},{"ph":"X","name":"unknown","pid":25110,"tid":25229,"ts":1819253.3739995493,"dur":198.0500045776367,"args":{"source_location":"unknown:0:0"}},{"ph":"X","name":"unknown","pid":25110,"tid":25229,"ts":1819540.6840047373,"dur":186.70000061035157,"args":{"source_location":"unknown:0:0"}},{"ph":"M","name":"process_name","pid":25110,"args":{"name":"Head Process"}},{"ph":"M","name":"process_sort_index","pid":25110,"args":{"sort_index":0}},{"ph":"M","name":"thread_name","pid":25110,"tid":25110,"args":{"name":"Control Thread"}},{"ph":"M","name":"thread_sort_index","pid":25110,"tid":25110,"args":{"sort_index":32767}},{"ph":"M","name":"thread_name","pid":25110,"tid":25111,"args":{"name":"Heartbeat Thread"}},{"ph":"M","name":"thread_sort_index","pid":25110,"tid":25111,"args":{"sort_index":32768}},{"ph":"M","name":"thread_name","pid":25110,"tid":25112,"args":{"name":"Failure Handler Thread"}},{"ph":"M","name":"thread_sort_index","pid":25110,"tid":25112,"args":{"sort_index":32769}},{"ph":"M","name":"thread_name","pid":25110,"tid":25226,"args":{"name":"Worker Thread"}},{"ph":"M","name":"thread_sort_index","pid":25110,"tid":25226,"args":{"sort_index":32767}},{"ph":"M","name":"thread_name","pid":25110,"tid":25231,"args":{"name":"Worker Thread"}},{"ph":"M","name":"thread_sort_index","pid":25110,"tid":25231,"args":{"sort_index":32767}},{"ph":"M","name":"thread_name","pid":25110,"tid":25227,"args":{"name":"Worker Thread"}},{"ph":"M","name":"thread_sort_index","pid":25110,"tid":25227,"args":{"sort_index":32767}},{"ph":"M","name":"thread_name","pid":25110,"tid":25229,"args":{"name":"Worker Thread"}},{"ph":"M","name":"thread_sort_index","pid":25110,"tid":25229,"args":{"sort_index":32767}},{"ph":"X","name":"Submit","pid":25110,"tid":25226,"ts":41528.371002197266,"dur":157.78000244140276,"args":{"Destinations":[1],"Location":"Origin","Origin":0,"mpi_tag":5}},{"ph":"X","name":"Submit","pid":25110,"tid":25226,"ts":42200.92100524902,"dur":779.2400015258754,"args":{"Destinations":[1],"Location":"Origin","Origin":0,"mpi_tag":6}},{"ph":"X","name":"Execute","pid":25110,"tid":25226,"ts":43068.84100341797,"dur":2481002.424003601,"args":{"Destinations":[1],"Location":"Origin","Origin":0,"mpi_tag":7,"task_id":486}},{"ph":"X","name":"Retrieve","pid":25110,"tid":25226,"ts":2524327.8950042725,"dur":259.6599987791851,"args":{"Destinations":[1],"Location":"Origin","Origin":0,"mpi_tag":9}},{"ph":"X","name":"Submit","pid":25110,"tid":25226,"ts":2525157.1450042725,"dur":157.6100021363236,"args":{"Destinations":[1],"Location":"Origin","Origin":0,"mpi_tag":31}},{"ph":"X","name":"Execute","pid":25110,"tid":25226,"ts":2525397.835006714,"dur":2686951.6199978637,"args":{"Destinations":[1],"Location":"Origin","Origin":0,"mpi_tag":32,"task_id":487}},{"ph":"X","name":"Retrieve","pid":25110,"tid":25226,"ts":5212513.535003662,"dur":297.38999877963215,"args":{"Destinations":[1],"Location":"Origin","Origin":0,"mpi_tag":33}},{"ph":"X","name":"Delete","pid":25110,"tid":25226,"ts":5212908.755004883,"dur":196.45999725349247,"args":{"Destinations":[1],"Location":"Origin","Origin":0,"mpi_tag":34}},{"ph":"X","name":"Submit","pid":25110,"tid":25231,"ts":40735.521003723145,"dur":619.0800033569321,"args":{"Destinations":[1],"Location":"Origin","Origin":0,"mpi_tag":11}},{"ph":"X","name":"Submit","pid":25110,"tid":25231,"ts":41784.79100036621,"dur":303.11000091552705,"args":{"Destinations":[1],"Location":"Origin","Origin":0,"mpi_tag":12}},{"ph":"X","name":"Execute","pid":25110,"tid":25231,"ts":42224.39100646973,"dur":1177449.1149951173,"args":{"Destinations":[1],"Location":"Origin","Origin":0,"mpi_tag":13,"task_id":484}},{"ph":"X","name":"Retrieve","pid":25110,"tid":25231,"ts":1219994.0760040283,"dur":92020.77299926756,"args":{"Destinations":[1],"Location":"Origin","Origin":0,"mpi_tag":14}},{"ph":"X","name":"Submit","pid":25110,"tid":25231,"ts":1312733.949005127,"dur":99137.43300231942,"args":{"Destinations":[1],"Location":"Origin","Origin":0,"mpi_tag":23}},{"ph":"X","name":"Submit","pid":25110,"tid":25231,"ts":1413471.7320022583,"dur":407.1500042723492,"args":{"Destinations":[1],"Location":"Origin","Origin":0,"mpi_tag":24}},{"ph":"X","name":"Execute","pid":25110,"tid":25231,"ts":1413974.7420043945,"dur":2509966.284998779,"args":{"Destinations":[1],"Location":"Origin","Origin":0,"mpi_tag":25,"task_id":485}},{"ph":"X","name":"Retrieve","pid":25110,"tid":25231,"ts":3924122.677001953,"dur":233.7999996948056,"args":{"Destinations":[1],"Location":"Origin","Origin":0,"mpi_tag":26}},{"ph":"X","name":"Alloc","pid":25110,"tid":25227,"ts":40230.46100616455,"dur":265.8399999999965,"args":{"Destinations":[1],"Location":"Origin","Origin":0,"mpi_tag":1}},{"ph":"X","name":"Submit","pid":25110,"tid":25227,"ts":40622.72100067139,"dur":674.0400033569313,"args":{"Destinations":[1],"Location":"Origin","Origin":0,"mpi_tag":2}},{"ph":"X","name":"Submit","pid":25110,"tid":25227,"ts":41375.64100646973,"dur":245.0499978637672,"args":{"Destinations":[1],"Location":"Origin","Origin":0,"mpi_tag":3}},{"ph":"X","name":"Submit","pid":25110,"tid":25227,"ts":41707.261001586914,"dur":141.71000152587658,"args":{"Destinations":[1],"Location":"Origin","Origin":0,"mpi_tag":4}},{"ph":"X","name":"Execute","pid":25110,"tid":25227,"ts":42112.45100402832,"dur":572825.9969992065,"args":{"Destinations":[1],"Location":"Origin","Origin":0,"mpi_tag":8,"task_id":482}},{"ph":"X","name":"Retrieve","pid":25110,"tid":25227,"ts":616304.9080047607,"dur":266.6400021362351,"args":{"Destinations":[1],"Location":"Origin","Origin":0,"mpi_tag":10}},{"ph":"X","name":"Submit","pid":25110,"tid":25227,"ts":617149.3180007935,"dur":157.80000457761344,"args":{"Destinations":[1],"Location":"Origin","Origin":0,"mpi_tag":18}},{"ph":"X","name":"Submit","pid":25110,"tid":25227,"ts":617391.6980056763,"dur":161.52999816893134,"args":{"Destinations":[1],"Location":"Origin","Origin":0,"mpi_tag":19}},{"ph":"X","name":"Submit","pid":25110,"tid":25227,"ts":617640.3980026245,"dur":200.89000305172522,"args":{"Destinations":[1],"Location":"Origin","Origin":0,"mpi_tag":20}},{"ph":"X","name":"Execute","pid":25110,"tid":25227,"ts":617922.7080001831,"dur":2594265.378001709,"args":{"Destinations":[1],"Location":"Origin","Origin":0,"mpi_tag":21,"task_id":483}},{"ph":"X","name":"Retrieve","pid":25110,"tid":25227,"ts":3212399.455001831,"dur":273.5710033569485,"args":{"Destinations":[1],"Location":"Origin","Origin":0,"mpi_tag":22}},{"ph":"X","name":"Submit","pid":25110,"tid":25229,"ts":41967.15100097656,"dur":200.66999969482276,"args":{"Destinations":[1],"Location":"Origin","Origin":0,"mpi_tag":15}},{"ph":"X","name":"Execute","pid":25110,"tid":25229,"ts":42307.121002197266,"dur":1775556.9230050659,"args":{"Destinations":[1],"Location":"Origin","Origin":0,"mpi_tag":16,"task_id":488}},{"ph":"X","name":"Retrieve","pid":25110,"tid":25229,"ts":1818153.4440002441,"dur":528.7800003052689,"args":{"Destinations":[1],"Location":"Origin","Origin":0,"mpi_tag":17}},{"ph":"X","name":"Submit","pid":25110,"tid":25229,"ts":1819253.3740005493,"dur":198.05000457772985,"args":{"Destinations":[1],"Location":"Origin","Origin":0,"mpi_tag":27}},{"ph":"X","name":"Submit","pid":25110,"tid":25229,"ts":1819540.6840057373,"dur":186.70000061043538,"args":{"Destinations":[1],"Location":"Origin","Origin":0,"mpi_tag":28}},{"ph":"X","name":"Execute","pid":25110,"tid":25229,"ts":1819826.2540054321,"dur":2796225.603000488,"args":{"Destinations":[1],"Location":"Origin","Origin":0,"mpi_tag":29,"task_id":489}},{"ph":"X","name":"Retrieve","pid":25110,"tid":25229,"ts":4616290.997001648,"dur":336.53099883999676,"args":{"Destinations":[1],"Location":"Origin","Origin":0,"mpi_tag":30}},{"name":"edge","cat":"Tasks Dependencies","args":{},"id":"V488V48967287","pid":25110,"tid":25229,"ph":"f","bp":"e","ts":1819826.2540054321},{"name":"edge","cat":"Tasks Dependencies","args":{},"id":"V488V48967287","pid":25110,"tid":25229,"ph":"s","ts":1817862.2684503403},{"name":"edge","cat":"Tasks Dependencies","args":{},"id":"V486V48767287","pid":25110,"tid":25226,"ph":"f","bp":"e","ts":2525397.835006714},{"name":"edge","cat":"Tasks Dependencies","args":{},"id":"V486V48767287","pid":25110,"tid":25226,"ph":"s","ts":2524068.784004595},{"name":"edge","cat":"Tasks Dependencies","args":{},"id":"V484V48567287","pid":25110,"tid":25231,"ph":"f","bp":"e","ts":1413974.7420043945},{"name":"edge","cat":"Tasks Dependencies","args":{},"id":"V484V48567287","pid":25110,"tid":25231,"ph":"s","ts":1219672.328552472},{"name":"edge","cat":"Tasks Dependencies","args":{},"id":"V482V48367287","pid":25110,"tid":25227,"ph":"f","bp":"e","ts":617922.7080001831},{"name":"edge","cat":"Tasks Dependencies","args":{},"id":"V482V48367287","pid":25110,"tid":25227,"ph":"s","ts":614937.8751772378},{"name":"edge","cat":"Worker Process 0","args":{},"id":"12939","pid":25110,"tid":25227,"ph":"s","ts":42112.45100402832},{"name":"edge","cat":"Worker Process 0","args":{},"id":"12939","pid":2736,"tid":2739,"ph":"f","bp":"e","ts":43071.73099517822},{"name":"edge","cat":"Worker Process 0","args":{},"id":"22678","pid":2736,"tid":2739,"ph":"s","ts":614790.2262761112},{"name":"edge","cat":"Worker Process 0","args":{},"id":"22678","pid":25110,"tid":25227,"ph":"f","bp":"e","ts":614937.8751772378},{"name":"edge","cat":"Worker Process 0","args":{},"id":"78201","pid":25110,"tid":25231,"ph":"s","ts":42224.39100646973},{"name":"edge","cat":"Worker Process 0","args":{},"id":"78201","pid":2736,"tid":2739,"ph":"f","bp":"e","ts":614991.4580001831},{"name":"edge","cat":"Worker Process 0","args":{},"id":"42768","pid":2736,"tid":2739,"ph":"s","ts":1219498.981492055},{"name":"edge","cat":"Worker Process 0","args":{},"id":"42768","pid":25110,"tid":25231,"ph":"f","bp":"e","ts":1219672.328552472},{"name":"edge","cat":"Worker Process 0","args":{},"id":"43759","pid":25110,"tid":25229,"ph":"s","ts":42307.121002197266},{"name":"edge","cat":"Worker Process 0","args":{},"id":"43759","pid":2736,"tid":2739,"ph":"f","bp":"e","ts":1219721.236000061},{"name":"edge","cat":"Worker Process 0","args":{},"id":"75235","pid":2736,"tid":2739,"ph":"s","ts":1817742.025978673},{"name":"edge","cat":"Worker Process 0","args":{},"id":"75235","pid":25110,"tid":25229,"ph":"f","bp":"e","ts":1817862.2684503403},{"name":"edge","cat":"Worker Process 0","args":{},"id":"52063","pid":25110,"tid":25226,"ph":"s","ts":43068.84100341797},{"name":"edge","cat":"Worker Process 0","args":{},"id":"52063","pid":2736,"tid":2739,"ph":"f","bp":"e","ts":1817963.5439987183},{"name":"edge","cat":"Worker Process 0","args":{},"id":"45160","pid":2736,"tid":2739,"ph":"s","ts":2523917.249044307},{"name":"edge","cat":"Worker Process 0","args":{},"id":"45160","pid":25110,"tid":25226,"ph":"f","bp":"e","ts":2524068.784004595},{"name":"edge","cat":"Worker Process 0","args":{},"id":"52986","pid":25110,"tid":25227,"ph":"s","ts":617922.7080001831},{"name":"edge","cat":"Worker Process 0","args":{},"id":"52986","pid":2736,"tid":2739,"ph":"f","bp":"e","ts":2524085.664993286},{"name":"edge","cat":"Worker Process 0","args":{},"id":"36080","pid":2736,"tid":2739,"ph":"s","ts":3212059.118019145},{"name":"edge","cat":"Worker Process 0","args":{},"id":"36080","pid":25110,"tid":25227,"ph":"f","bp":"e","ts":3212185.491736514},{"name":"edge","cat":"Worker Process 0","args":{},"id":"60387","pid":25110,"tid":25231,"ph":"s","ts":1413974.7420043945},{"name":"edge","cat":"Worker Process 0","args":{},"id":"60387","pid":2736,"tid":2739,"ph":"f","bp":"e","ts":3212256.585998535},{"name":"edge","cat":"Worker Process 0","args":{},"id":"19110","pid":2736,"tid":2739,"ph":"s","ts":3923771.565482844},{"name":"edge","cat":"Worker Process 0","args":{},"id":"19110","pid":25110,"tid":25231,"ph":"f","bp":"e","ts":3923938.5170368887},{"name":"edge","cat":"Worker Process 0","args":{},"id":"14628","pid":25110,"tid":25229,"ph":"s","ts":1819826.2540054321},{"name":"edge","cat":"Worker Process 0","args":{},"id":"14628","pid":2736,"tid":2739,"ph":"f","bp":"e","ts":3924022.916999817},{"name":"edge","cat":"Worker Process 0","args":{},"id":"75634","pid":2736,"tid":2739,"ph":"s","ts":4612391.768630277},{"name":"edge","cat":"Worker Process 0","args":{},"id":"75634","pid":25110,"tid":25229,"ph":"f","bp":"e","ts":4616049.0607803175},{"name":"edge","cat":"Worker Process 0","args":{},"id":"56015","pid":25110,"tid":25226,"ph":"s","ts":2525397.835006714},{"name":"edge","cat":"Worker Process 0","args":{},"id":"56015","pid":2736,"tid":2739,"ph":"f","bp":"e","ts":4612594.236999512},{"name":"edge","cat":"Worker Process 0","args":{},"id":"69293","pid":2736,"tid":2739,"ph":"s","ts":5212156.885436263},{"name":"edge","cat":"Worker Process 0","args":{},"id":"69293","pid":25110,"tid":25226,"ph":"f","bp":"e","ts":5212346.768052958},{"name":"edge","cat":"Communication","args":{},"id":"62377","pid":2736,"tid":2740,"ph":"s","ts":40405.24099372752},{"name":"edge","cat":"Communication","args":{},"id":"62377","pid":2736,"tid":2740,"ph":"f","bp":"e","ts":40541.29099273682},{"name":"edge","cat":"Communication","args":{},"id":"54166","pid":2736,"tid":2740,"ph":"s","ts":40773.570995088216},{"name":"edge","cat":"Communication","args":{},"id":"54166","pid":2736,"tid":2740,"ph":"f","bp":"e","ts":40852.080993652344},{"name":"edge","cat":"Communication","args":{},"id":"24316","pid":2736,"tid":2740,"ph":"s","ts":40868.660997864805},{"name":"edge","cat":"Communication","args":{},"id":"24316","pid":2736,"tid":2740,"ph":"f","bp":"e","ts":41406.950996398926},{"name":"edge","cat":"Communication","args":{},"id":"09882","pid":2736,"tid":2740,"ph":"s","ts":41507.46099877033},{"name":"edge","cat":"Communication","args":{},"id":"09882","pid":2736,"tid":2740,"ph":"f","bp":"e","ts":41564.15099334717},{"name":"edge","cat":"Communication","args":{},"id":"34173","pid":2736,"tid":2740,"ph":"s","ts":41603.09099816998},{"name":"edge","cat":"Communication","args":{},"id":"34173","pid":2736,"tid":2740,"ph":"f","bp":"e","ts":41740.73099517822},{"name":"edge","cat":"Communication","args":{},"id":"23399","pid":2736,"tid":2740,"ph":"s","ts":41819.52099632892},{"name":"edge","cat":"Communication","args":{},"id":"23399","pid":2736,"tid":2740,"ph":"f","bp":"e","ts":41877.590995788574},{"name":"edge","cat":"Communication","args":{},"id":"29530","pid":2736,"tid":2740,"ph":"s","ts":41902.90099358234},{"name":"edge","cat":"Communication","args":{},"id":"29530","pid":2736,"tid":2740,"ph":"f","bp":"e","ts":41959.37099456787},{"name":"edge","cat":"Communication","args":{},"id":"37590","pid":2736,"tid":2740,"ph":"s","ts":42055.16099571857},{"name":"edge","cat":"Communication","args":{},"id":"37590","pid":2736,"tid":2740,"ph":"f","bp":"e","ts":42168.090995788574},{"name":"edge","cat":"Communication","args":{},"id":"96313","pid":2736,"tid":2740,"ph":"s","ts":42267.80099510822},{"name":"edge","cat":"Communication","args":{},"id":"96313","pid":2736,"tid":2740,"ph":"f","bp":"e","ts":43030.26099395752},{"name":"edge","cat":"Communication","args":{},"id":"37315","pid":2736,"tid":2740,"ph":"s","ts":616396.3579945499},{"name":"edge","cat":"Communication","args":{},"id":"37315","pid":2736,"tid":2740,"ph":"f","bp":"e","ts":616548.8879928589},{"name":"edge","cat":"Communication","args":{},"id":"87013","pid":2736,"tid":2740,"ph":"s","ts":617172.7980000931},{"name":"edge","cat":"Communication","args":{},"id":"87013","pid":2736,"tid":2740,"ph":"f","bp":"e","ts":617363.9779968262},{"name":"edge","cat":"Communication","args":{},"id":"51731","pid":2736,"tid":2740,"ph":"s","ts":617524.147993084},{"name":"edge","cat":"Communication","args":{},"id":"51731","pid":2736,"tid":2740,"ph":"f","bp":"e","ts":617566.6479949951},{"name":"edge","cat":"Communication","args":{},"id":"33119","pid":2736,"tid":2740,"ph":"s","ts":617812.127996441},{"name":"edge","cat":"Communication","args":{},"id":"33119","pid":2736,"tid":2740,"ph":"f","bp":"e","ts":617849.0579986572},{"name":"edge","cat":"Communication","args":{},"id":"78305","pid":2736,"tid":2740,"ph":"s","ts":1311921.5689968925},{"name":"edge","cat":"Communication","args":{},"id":"78305","pid":2736,"tid":2740,"ph":"f","bp":"e","ts":1312004.388999939},{"name":"edge","cat":"Communication","args":{},"id":"85417","pid":2736,"tid":2740,"ph":"s","ts":1408836.9419991819},{"name":"edge","cat":"Communication","args":{},"id":"85417","pid":2736,"tid":2740,"ph":"f","bp":"e","ts":1408997.981994629},{"name":"edge","cat":"Communication","args":{},"id":"79313","pid":2736,"tid":2740,"ph":"s","ts":1413875.9919950892},{"name":"edge","cat":"Communication","args":{},"id":"79313","pid":2736,"tid":2740,"ph":"f","bp":"e","ts":1413914.1519927979},{"name":"edge","cat":"Communication","args":{},"id":"55431","pid":2736,"tid":2740,"ph":"s","ts":1818333.2039956916},{"name":"edge","cat":"Communication","args":{},"id":"55431","pid":2736,"tid":2740,"ph":"f","bp":"e","ts":1818476.3339996338},{"name":"edge","cat":"Communication","args":{},"id":"26240","pid":2736,"tid":2740,"ph":"s","ts":1819414.303992505},{"name":"edge","cat":"Communication","args":{},"id":"26240","pid":2736,"tid":2740,"ph":"f","bp":"e","ts":1819464.8239974976},{"name":"edge","cat":"Communication","args":{},"id":"10622","pid":2736,"tid":2740,"ph":"s","ts":1819705.3239934403},{"name":"edge","cat":"Communication","args":{},"id":"10622","pid":2736,"tid":2740,"ph":"f","bp":"e","ts":1819742.5439987183},{"name":"edge","cat":"Communication","args":{},"id":"38286","pid":2736,"tid":2740,"ph":"s","ts":2524495.174998509},{"name":"edge","cat":"Communication","args":{},"id":"38286","pid":2736,"tid":2740,"ph":"f","bp":"e","ts":2524534.9049987793},{"name":"edge","cat":"Communication","args":{},"id":"48617","pid":2736,"tid":2740,"ph":"s","ts":2525294.4349935013},{"name":"edge","cat":"Communication","args":{},"id":"48617","pid":2736,"tid":2740,"ph":"f","bp":"e","ts":2525367.9549942017},{"name":"edge","cat":"Communication","args":{},"id":"66143","pid":2736,"tid":2740,"ph":"s","ts":3212514.785997678},{"name":"edge","cat":"Communication","args":{},"id":"66143","pid":2736,"tid":2740,"ph":"f","bp":"e","ts":3212610.8549957275},{"name":"edge","cat":"Communication","args":{},"id":"85531","pid":2736,"tid":2740,"ph":"s","ts":3924244.716999517},{"name":"edge","cat":"Communication","args":{},"id":"85531","pid":2736,"tid":2740,"ph":"f","bp":"e","ts":3924368.2169952393},{"name":"edge","cat":"Communication","args":{},"id":"28863","pid":2736,"tid":2740,"ph":"s","ts":4616524.367994118},{"name":"edge","cat":"Communication","args":{},"id":"28863","pid":2736,"tid":2740,"ph":"f","bp":"e","ts":4616572.996994019},{"name":"edge","cat":"Communication","args":{},"id":"74108","pid":2736,"tid":2740,"ph":"s","ts":5212709.434994207},{"name":"edge","cat":"Communication","args":{},"id":"74108","pid":2736,"tid":2740,"ph":"f","bp":"e","ts":5212753.684997559},{"name":"edge","cat":"Communication","args":{},"id":"12322","pid":2736,"tid":2740,"ph":"s","ts":5213035.684996839},{"name":"edge","cat":"Communication","args":{},"id":"12322","pid":2736,"tid":2740,"ph":"f","bp":"e","ts":5213133.26499939},{"ph":"X","name":"Alloc / Begin","pid":2736,"tid":2740,"ts":40405.01099395752,"dur":0.23,"args":{"Destinations":[1],"Location":"Destination","Origin":0,"mpi_tag":1}},{"ph":"X","name":"Submit / Begin","pid":2736,"tid":2740,"ts":40773.48099517822,"dur":0.09,"args":{"Destinations":[1],"Location":"Destination","Origin":0,"mpi_tag":2}},{"ph":"X","name":"Submit / Begin","pid":2736,"tid":2740,"ts":40868.600997924805,"dur":0.06,"args":{"Destinations":[1],"Location":"Destination","Origin":0,"mpi_tag":11}},{"ph":"X","name":"Submit / Begin","pid":2736,"tid":2740,"ts":41507.39099884033,"dur":0.07,"args":{"Destinations":[1],"Location":"Destination","Origin":0,"mpi_tag":3}},{"ph":"X","name":"Submit / Begin","pid":2736,"tid":2740,"ts":41603.03099822998,"dur":0.06,"args":{"Destinations":[1],"Location":"Destination","Origin":0,"mpi_tag":5}},{"ph":"X","name":"Submit / Begin","pid":2736,"tid":2740,"ts":41819.450996398926,"dur":0.07,"args":{"Destinations":[1],"Location":"Destination","Origin":0,"mpi_tag":4}},{"ph":"X","name":"Submit / Begin","pid":2736,"tid":2740,"ts":41902.830993652344,"dur":0.07,"args":{"Destinations":[1],"Location":"Destination","Origin":0,"mpi_tag":12}},{"ph":"X","name":"Submit / Begin","pid":2736,"tid":2740,"ts":42055.090995788574,"dur":0.07,"args":{"Destinations":[1],"Location":"Destination","Origin":0,"mpi_tag":15}},{"ph":"X","name":"Submit / Begin","pid":2736,"tid":2740,"ts":42267.73099517822,"dur":0.07,"args":{"Destinations":[1],"Location":"Destination","Origin":0,"mpi_tag":6}},{"ph":"X","name":"Retrieve / Begin","pid":2736,"tid":2740,"ts":616396.2179946899,"dur":0.14,"args":{"Destinations":[1],"Location":"Destination","Origin":0,"mpi_tag":10}},{"ph":"X","name":"Submit / Begin","pid":2736,"tid":2740,"ts":617172.7080001831,"dur":0.09,"args":{"Destinations":[1],"Location":"Destination","Origin":0,"mpi_tag":18}},{"ph":"X","name":"Submit / Begin","pid":2736,"tid":2740,"ts":617524.0679931641,"dur":0.08,"args":{"Destinations":[1],"Location":"Destination","Origin":0,"mpi_tag":19}},{"ph":"X","name":"Submit / Begin","pid":2736,"tid":2740,"ts":617812.047996521,"dur":0.08,"args":{"Destinations":[1],"Location":"Destination","Origin":0,"mpi_tag":20}},{"ph":"X","name":"Retrieve / Begin","pid":2736,"tid":2740,"ts":1311921.2689971924,"dur":0.3,"args":{"Destinations":[1],"Location":"Destination","Origin":0,"mpi_tag":14}},{"ph":"X","name":"Submit / Begin","pid":2736,"tid":2740,"ts":1408836.6119995117,"dur":0.33,"args":{"Destinations":[1],"Location":"Destination","Origin":0,"mpi_tag":23}},{"ph":"X","name":"Submit / Begin","pid":2736,"tid":2740,"ts":1413875.8419952393,"dur":0.15,"args":{"Destinations":[1],"Location":"Destination","Origin":0,"mpi_tag":24}},{"ph":"X","name":"Retrieve / Begin","pid":2736,"tid":2740,"ts":1818332.9239959717,"dur":0.28,"args":{"Destinations":[1],"Location":"Destination","Origin":0,"mpi_tag":17}},{"ph":"X","name":"Submit / Begin","pid":2736,"tid":2740,"ts":1819414.1939926147,"dur":0.11,"args":{"Destinations":[1],"Location":"Destination","Origin":0,"mpi_tag":27}},{"ph":"X","name":"Submit / Begin","pid":2736,"tid":2740,"ts":1819705.2339935303,"dur":0.09,"args":{"Destinations":[1],"Location":"Destination","Origin":0,"mpi_tag":28}},{"ph":"X","name":"Retrieve / Begin","pid":2736,"tid":2740,"ts":2524494.9049987793,"dur":0.27,"args":{"Destinations":[1],"Location":"Destination","Origin":0,"mpi_tag":9}},{"ph":"X","name":"Submit / Begin","pid":2736,"tid":2740,"ts":2525294.3449935913,"dur":0.09,"args":{"Destinations":[1],"Location":"Destination","Origin":0,"mpi_tag":31}},{"ph":"X","name":"Retrieve / Begin","pid":2736,"tid":2740,"ts":3212514.294998169,"dur":0.491,"args":{"Destinations":[1],"Location":"Destination","Origin":0,"mpi_tag":22}},{"ph":"X","name":"Retrieve / Begin","pid":2736,"tid":2740,"ts":3924244.416999817,"dur":0.3,"args":{"Destinations":[1],"Location":"Destination","Origin":0,"mpi_tag":26}},{"ph":"X","name":"Retrieve / Begin","pid":2736,"tid":2740,"ts":4616523.856994629,"dur":0.511,"args":{"Destinations":[1],"Location":"Destination","Origin":0,"mpi_tag":30}},{"ph":"X","name":"Retrieve / Begin","pid":2736,"tid":2740,"ts":5212709.134994507,"dur":0.3,"args":{"Destinations":[1],"Location":"Destination","Origin":0,"mpi_tag":33}},{"ph":"X","name":"Delete / Begin","pid":2736,"tid":2740,"ts":5213035.574996948,"dur":0.11,"args":{"Destinations":[1],"Location":"Destination","Origin":0,"mpi_tag":34}},{"ph":"X","name":"Alloc / End","pid":2736,"tid":2740,"ts":40541.29099273682,"dur":0.1,"args":{"Destinations":[1],"Location":"Destination","Origin":0,"mpi_tag":1}},{"ph":"X","name":"Submit / End","pid":2736,"tid":2740,"ts":40852.080993652344,"dur":0.07,"args":{"Destinations":[1],"Location":"Destination","Origin":0,"mpi_tag":2}},{"ph":"X","name":"Submit / End","pid":2736,"tid":2740,"ts":41406.950996398926,"dur":0.08,"args":{"Destinations":[1],"Location":"Destination","Origin":0,"mpi_tag":11}},{"ph":"X","name":"Submit / End","pid":2736,"tid":2740,"ts":41564.15099334717,"dur":0.11,"args":{"Destinations":[1],"Location":"Destination","Origin":0,"mpi_tag":3}},{"ph":"X","name":"Submit / End","pid":2736,"tid":2740,"ts":41740.73099517822,"dur":0.12,"args":{"Destinations":[1],"Location":"Destination","Origin":0,"mpi_tag":5}},{"ph":"X","name":"Submit / End","pid":2736,"tid":2740,"ts":41877.590995788574,"dur":0.08,"args":{"Destinations":[1],"Location":"Destination","Origin":0,"mpi_tag":4}},{"ph":"X","name":"Submit / End","pid":2736,"tid":2740,"ts":41959.37099456787,"dur":0.07,"args":{"Destinations":[1],"Location":"Destination","Origin":0,"mpi_tag":12}},{"ph":"X","name":"Submit / End","pid":2736,"tid":2740,"ts":42168.090995788574,"dur":0.06,"args":{"Destinations":[1],"Location":"Destination","Origin":0,"mpi_tag":15}},{"ph":"X","name":"Submit / End","pid":2736,"tid":2740,"ts":43030.26099395752,"dur":0.1,"args":{"Destinations":[1],"Location":"Destination","Origin":0,"mpi_tag":6}},{"ph":"X","name":"Retrieve / End","pid":2736,"tid":2740,"ts":616548.8879928589,"dur":0.09,"args":{"Destinations":[1],"Location":"Destination","Origin":0,"mpi_tag":10}},{"ph":"X","name":"Submit / End","pid":2736,"tid":2740,"ts":617363.9779968262,"dur":0.11,"args":{"Destinations":[1],"Location":"Destination","Origin":0,"mpi_tag":18}},{"ph":"X","name":"Submit / End","pid":2736,"tid":2740,"ts":617566.6479949951,"dur":0.06,"args":{"Destinations":[1],"Location":"Destination","Origin":0,"mpi_tag":19}},{"ph":"X","name":"Submit / End","pid":2736,"tid":2740,"ts":617849.0579986572,"dur":0.07,"args":{"Destinations":[1],"Location":"Destination","Origin":0,"mpi_tag":20}},{"ph":"X","name":"Retrieve / End","pid":2736,"tid":2740,"ts":1312004.388999939,"dur":0.11,"args":{"Destinations":[1],"Location":"Destination","Origin":0,"mpi_tag":14}},{"ph":"X","name":"Submit / End","pid":2736,"tid":2740,"ts":1408997.981994629,"dur":0.11,"args":{"Destinations":[1],"Location":"Destination","Origin":0,"mpi_tag":23}},{"ph":"X","name":"Submit / End","pid":2736,"tid":2740,"ts":1413914.1519927979,"dur":0.11,"args":{"Destinations":[1],"Location":"Destination","Origin":0,"mpi_tag":24}},{"ph":"X","name":"Retrieve / End","pid":2736,"tid":2740,"ts":1818476.3339996338,"dur":0.1,"args":{"Destinations":[1],"Location":"Destination","Origin":0,"mpi_tag":17}},{"ph":"X","name":"Submit / End","pid":2736,"tid":2740,"ts":1819464.8239974976,"dur":0.1,"args":{"Destinations":[1],"Location":"Destination","Origin":0,"mpi_tag":27}},{"ph":"X","name":"Submit / End","pid":2736,"tid":2740,"ts":1819742.5439987183,"dur":0.07,"args":{"Destinations":[1],"Location":"Destination","Origin":0,"mpi_tag":28}},{"ph":"X","name":"Retrieve / End","pid":2736,"tid":2740,"ts":2524534.9049987793,"dur":0.1,"args":{"Destinations":[1],"Location":"Destination","Origin":0,"mpi_tag":9}},{"ph":"X","name":"Submit / End","pid":2736,"tid":2740,"ts":2525367.9549942017,"dur":0.08,"args":{"Destinations":[1],"Location":"Destination","Origin":0,"mpi_tag":31}},{"ph":"X","name":"Retrieve / End","pid":2736,"tid":2740,"ts":3212610.8549957275,"dur":0.091,"args":{"Destinations":[1],"Location":"Destination","Origin":0,"mpi_tag":22}},{"ph":"X","name":"Retrieve / End","pid":2736,"tid":2740,"ts":3924368.2169952393,"dur":0.11,"args":{"Destinations":[1],"Location":"Destination","Origin":0,"mpi_tag":26}},{"ph":"X","name":"Retrieve / End","pid":2736,"tid":2740,"ts":4616572.996994019,"dur":0.091,"args":{"Destinations":[1],"Location":"Destination","Origin":0,"mpi_tag":30}},{"ph":"X","name":"Retrieve / End","pid":2736,"tid":2740,"ts":5212753.684997559,"dur":0.1,"args":{"Destinations":[1],"Location":"Destination","Origin":0,"mpi_tag":33}},{"ph":"X","name":"Delete / End","pid":2736,"tid":2740,"ts":5213133.26499939,"dur":0.1,"args":{"Destinations":[1],"Location":"Destination","Origin":0,"mpi_tag":34}}]}