{"traceEvents":[{"ph":"X","name":"OMPC Runtime Execution","pid":2352,"tid":2352,"ts":0.0,"dur":5912021.406,"args":{}},{"ph":"X","name":"Task 484","pid":2352,"tid":2355,"ts":75671.88199615479,"dur":739385.062,"args":{"mpi_tag":5,"target_region_index":0,"source_location":"unknown:0:0"},"cname":"yellow"},{"ph":"X","name":"Task 488","pid":2352,"tid":2355,"ts":815236.2539978027,"dur":696638.421,"args":{"mpi_tag":9,"target_region_index":0,"source_location":"unknown:0:0"},"cname":"yellow"},{"ph":"X","name":"Task 490","pid":2352,"tid":2355,"ts":1512562.214996338,"dur":706818.381,"args":{"mpi_tag":16,"target_region_index":0,"source_location":"unknown:0:0"},"cname":"yellow"},{"ph":"X","name":"Task 486","pid":2352,"tid":2355,"ts":2219622.6060028076,"dur":790533.523,"args":{"mpi_tag":13,"target_region_index":0,"source_location":"unknown:0:0"},"cname":"yellow"},{"ph":"X","name":"Task 485","pid":2352,"tid":2355,"ts":3010351.839996338,"dur":701083.91,"args":{"mpi_tag":21,"target_region_index":0,"source_location":"unknown:0:0"},"cname":"yellow"},{"ph":"X","name":"Task 489","pid":2352,"tid":2355,"ts":3711611.769996643,"dur":698507.181,"args":{"mpi_tag":25,"target_region_index":0,"source_location":"unknown:0:0"},"cname":"yellow"},{"ph":"X","name":"Task 491","pid":2352,"tid":2355,"ts":4410400.691001892,"dur":703716.571,"args":{"mpi_tag":29,"target_region_index":0,"source_location":"unknown:0:0"},"cname":"yellow"},{"ph":"X","name":"Task 487","pid":2352,"tid":2355,"ts":5114310.592002869,"dur":703806.011,"args":{"mpi_tag":32,"target_region_index":0,"source_location":"unknown:0:0"},"cname":"yellow"},{"ph":"M","name":"process_name","pid":2352,"args":{"name":"Worker Process 0"}},{"ph":"M","name":"process_sort_index","pid":2352,"args":{"sort_index":1}},{"ph":"M","name":"thread_name","pid":2352,"tid":2352,"args":{"name":"Gate Thread"}},{"ph":"M","name":"thread_sort_index","pid":2352,"tid":2352,"args":{"sort_index":32767}},{"ph":"M","name":"thread_name","pid":2352,"tid":2353,"args":{"name":"Heartbeat Thread"}},{"ph":"M","name":"thread_sort_index","pid":2352,"tid":2353,"args":{"sort_index":32768}},{"ph":"M","name":"thread_name","pid":2352,"tid":2354,"args":{"name":"Failure Handler Thread"}},{"ph":"M","name":"thread_sort_index","pid":2352,"tid":2354,"args":{"sort_index":32769}},{"ph":"M","name":"thread_name","pid":2352,"tid":2355,"args":{"name":"Execute Event Handler 0"}},{"ph":"M","name":"thread_sort_index","pid":2352,"tid":2355,"args":{"sort_index":32767}},{"ph":"M","name":"thread_name","pid":2352,"tid":2356,"args":{"name":"Data Event Handler 0"}},{"ph":"M","name":"thread_sort_index","pid":2352,"tid":2356,"args":{"sort_index":32767}},{"ph":"X","name":"OMPC Runtime Execution","pid":24294,"tid":24294,"ts":0.0,"dur":5912181.316,"args":{}},{"ph":"X","name":"unknown","pid":24294,"tid":24413,"ts":74701.40199942725,"dur":241.3299987792969,"args":{"source_location":"unknown:0:0"}},{"ph":"X","name":"unknown","pid":24294,"tid":24413,"ts":75032.03199668067,"dur":213.6599966430664,"args":{"source_location":"unknown:0:0"}},{"ph":"X","name":"unknown","pid":24294,"tid":24413,"ts":75327.96199698585,"dur":208.25999938964844,"args":{"source_location":"unknown:0:0"}},{"ph":"X","name":"unknown","pid":24294,"tid":24413,"ts":819176.7239980234,"dur":204.90000091552736,"args":{"source_location":"unknown:0:0"}},{"ph":"X","name":"unknown","pid":24294,"tid":24413,"ts":819471.953993751,"dur":143.4000030517578,"args":{"source_location":"unknown:0:0"}},{"ph":"X","name":"unknown","pid":24294,"tid":24413,"ts":819703.5839986338,"dur":95543.75299591065,"args":{"source_location":"unknown:0:0"}},{"ph":"X","name":"unknown","pid":24294,"tid":24409,"ts":76247.95199484962,"dur":890.3000003051758,"args":{"source_location":"unknown:0:0"}},{"ph":"X","name":"unknown","pid":24294,"tid":24409,"ts":77228.83199973243,"dur":135.72999603271484,"args":{"source_location":"unknown:0:0"}},{"ph":"X","name":"unknown","pid":24294,"tid":24409,"ts":1515696.9649953379,"dur":416.17999755859375,"args":{"source_location":"unknown:0:0"}},{"ph":"X","name":"unknown","pid":24294,"tid":24409,"ts":1516196.8049993052,"dur":359.5499969482422,"args":{"source_location":"unknown:0:0"}},{"ph":"X","name":"unknown","pid":24294,"tid":24411,"ts":77479.73199362891,"dur":188.24000061035156,"args":{"source_location":"unknown:0:0"}},{"ph":"X","name":"unknown","pid":24294,"tid":24411,"ts":78033.13199515479,"dur":234.1899984741211,"args":{"source_location":"unknown:0:0"}},{"ph":"X","name":"unknown","pid":24294,"tid":24411,"ts":3011553.569998695,"dur":137.67999420166015,"args":{"source_location":"unknown:0:0"}},{"ph":"X","name":"unknown","pid":24294,"tid":24412,"ts":77916.15199942725,"dur":230.99999603271485,"args":{"source_location":"unknown:0:0"}},{"ph":"X","name":"unknown","pid":24294,"tid":24412,"ts":2221024.4359960095,"dur":215.99999938964845,"args":{"source_location":"unknown:0:0"}},{"ph":"X","name":"unknown","pid":24294,"tid":24412,"ts":2221393.225996925,"dur":181.60000213623047,"args":{"source_location":"unknown:0:0"}},{"ph":"M","name":"process_name","pid":24294,"args":{"name":"Head Process"}},{"ph":"M","name":"process_sort_index","pid":24294,"args":{"sort_index":0}},{"ph":"M","name":"thread_name","pid":24294,"tid":24294,"args":{"name":"Control Thread"}},{"ph":"M","name":"thread_sort_index","pid":24294,"tid":24294,"args":{"sort_index":32767}},{"ph":"M","name":"thread_name","pid":24294,"tid":24295,"args":{"name":"Heartbeat Thread"}},{"ph":"M","name":"thread_sort_index","pid":24294,"tid":24295,"args":{"sort_index":32768}},{"ph":"M","name":"thread_name","pid":24294,"tid":24296,"args":{"name":"Failure Handler Thread"}},{"ph":"M","name":"thread_sort_index","pid":24294,"tid":24296,"args":{"sort_index":32769}},{"ph":"M","name":"thread_name","pid":24294,"tid":24413,"args":{"name":"Worker Thread"}},{"ph":"M","name":"thread_sort_index","pid":24294,"tid":24413,"args":{"sort_index":32767}},{"ph":"M","name":"thread_name","pid":24294,"tid":24409,"args":{"name":"Worker Thread"}},{"ph":"M","name":"thread_sort_index","pid":24294,"tid":24409,"args":{"sort_index":32767}},{"ph":"M","name":"thread_name","pid":24294,"tid":24411,"args":{"name":"Worker Thread"}},{"ph":"M","name":"thread_sort_index","pid":24294,"tid":24411,"args":{"sort_index":32767}},{"ph":"M","name":"thread_name","pid":24294,"tid":24412,"args":{"name":"Worker Thread"}},{"ph":"M","name":"thread_sort_index","pid":24294,"tid":24412,"args":{"sort_index":32767}},{"ph":"X","name":"Alloc","pid":24294,"tid":24413,"ts":74103.47200012207,"dur":478.0199945068307,"args":{"Destinations":[1],"Location":"Origin","Origin":0,"mpi_tag":1}},{"ph":"X","name":"Submit","pid":24294,"tid":24413,"ts":74701.40200042725,"dur":241.32999877929979,"args":{"Destinations":[1],"Location":"Origin","Origin":0,"mpi_tag":2}},{"ph":"X","name":"Submit","pid":24294,"tid":24413,"ts":75032.03199768066,"dur":213.65999664306582,"args":{"Destinations":[1],"Location":"Origin","Origin":0,"mpi_tag":3}},{"ph":"X","name":"Submit","pid":24294,"tid":24413,"ts":75327.96199798584,"dur":208.25999938964378,"args":{"Destinations":[1],"Location":"Origin","Origin":0,"mpi_tag":4}},{"ph":"X","name":"Execute","pid":24294,"tid":24413,"ts":75612.34199523926,"dur":739741.7520037842,"args":{"Destinations":[1],"Location":"Origin","Origin":0,"mpi_tag":5,"task_id":484}},{"ph":"X","name":"Retrieve","pid":24294,"tid":24413,"ts":818404.9039993286,"dur":325.45999633788597,"args":{"Destinations":[1],"Location":"Origin","Origin":0,"mpi_tag":6}},{"ph":"X","name":"Submit","pid":24294,"tid":24413,"ts":819176.7239990234,"dur":204.90000091551337,"args":{"Destinations":[1],"Location":"Origin","Origin":0,"mpi_tag":18}},{"ph":"X","name":"Submit","pid":24294,"tid":24413,"ts":819471.953994751,"dur":143.40000305173453,"args":{"Destinations":[1],"Location":"Origin","Origin":0,"mpi_tag":19}},{"ph":"X","name":"Submit","pid":24294,"tid":24413,"ts":819703.5839996338,"dur":95543.75299591059,"args":{"Destinations":[1],"Location":"Origin","Origin":0,"mpi_tag":20}},{"ph":"X","name":"Execute","pid":24294,"tid":24413,"ts":915436.5069961548,"dur":2796300.9630029295,"args":{"Destinations":[1],"Location":"Origin","Origin":0,"mpi_tag":21,"task_id":485}},{"ph":"X","name":"Retrieve","pid":24294,"tid":24413,"ts":3711971.5499954224,"dur":99041.47400353989,"args":{"Destinations":[1],"Location":"Origin","Origin":0,"mpi_tag":22}},{"ph":"X","name":"Submit","pid":24294,"tid":24409,"ts":76247.95199584961,"dur":890.3000003051711,"args":{"Destinations":[1],"Location":"Origin","Origin":0,"mpi_tag":7}},{"ph":"X","name":"Submit","pid":24294,"tid":24409,"ts":77228.83200073242,"dur":135.72999603272183,"args":{"Destinations":[1],"Location":"Origin","Origin":0,"mpi_tag":8}},{"ph":"X","name":"Execute","pid":24294,"tid":24409,"ts":77741.59199523926,"dur":1436617.6930029297,"args":{"Destinations":[1],"Location":"Origin","Origin":0,"mpi_tag":9,"task_id":488}},{"ph":"X","name":"Retrieve","pid":24294,"tid":24409,"ts":1514630.3050003052,"dur":233.48999938974157,"args":{"Destinations":[1],"Location":"Origin","Origin":0,"mpi_tag":10}},{"ph":"X","name":"Submit","pid":24294,"tid":24409,"ts":1515696.964996338,"dur":416.1799975587055,"args":{"Destinations":[1],"Location":"Origin","Origin":0,"mpi_tag":23}},{"ph":"X","name":"Submit","pid":24294,"tid":24409,"ts":1516196.8050003052,"dur":359.5499969483353,"args":{"Destinations":[1],"Location":"Origin","Origin":0,"mpi_tag":24}},{"ph":"X","name":"Execute","pid":24294,"tid":24409,"ts":1516639.8549957275,"dur":2894165.5860037236,"args":{"Destinations":[1],"Location":"Origin","Origin":0,"mpi_tag":25,"task_id":489}},{"ph":"X","name":"Retrieve","pid":24294,"tid":24409,"ts":4411065.700996399,"dur":313.2200009152293,"args":{"Destinations":[1],"Location":"Origin","Origin":0,"mpi_tag":26}},{"ph":"X","name":"Submit","pid":24294,"tid":24411,"ts":77479.7319946289,"dur":188.24000061035622,"args":{"Destinations":[1],"Location":"Origin","Origin":0,"mpi_tag":11}},{"ph":"X","name":"Submit","pid":24294,"tid":24411,"ts":78033.13199615479,"dur":234.1899984741176,"args":{"Destinations":[1],"Location":"Origin","Origin":0,"mpi_tag":12}},{"ph":"X","name":"Execute","pid":24294,"tid":24411,"ts":78412.08200073242,"dur":2932036.537998657,"args":{"Destinations":[1],"Location":"Origin","Origin":0,"mpi_tag":13,"task_id":486}},{"ph":"X","name":"Retrieve","pid":24294,"tid":24411,"ts":3010593.1689987183,"dur":383.11999572766945,"args":{"Destinations":[1],"Location":"Origin","Origin":0,"mpi_tag":14}},{"ph":"X","name":"Submit","pid":24294,"tid":24411,"ts":3011553.569999695,"dur":137.6799942017533,"args":{"Destinations":[1],"Location":"Origin","Origin":0,"mpi_tag":31}},{"ph":"X","name":"Execute","pid":24294,"tid":24411,"ts":3011777.7799987793,"dur":2810559.373001404,"args":{"Destinations":[1],"Location":"Origin","Origin":0,"mpi_tag":32,"task_id":487}},{"ph":"X","name":"Retrieve","pid":24294,"tid":24411,"ts":5822557.8829956055,"dur":681.3800042727962,"args":{"Destinations":[1],"Location":"Origin","Origin":0,"mpi_tag":33}},{"ph":"X","name":"Delete","pid":24294,"tid":24411,"ts":5823365.412994385,"dur":87102.90300384536,"args":{"Destinations":[1],"Location":"Origin","Origin":0,"mpi_tag":34}},{"ph":"X","name":"Submit","pid":24294,"tid":24412,"ts":77916.15200042725,"dur":230.99999603271135,"args":{"Destinations":[1],"Location":"Origin","Origin":0,"mpi_tag":15}},{"ph":"X","name":"Execute","pid":24294,"tid":24412,"ts":78293.31199645996,"dur":2141421.593998718,"args":{"Destinations":[1],"Location":"Origin","Origin":0,"mpi_tag":16,"task_id":490}},{"ph":"X","name":"Retrieve","pid":24294,"tid":24412,"ts":2219929.4559936523,"dur":278.020005798433,"args":{"Destinations":[1],"Location":"Origin","Origin":0,"mpi_tag":17}},{"ph":"X","name":"Submit","pid":24294,"tid":24412,"ts":2221024.4359970093,"dur":215.99999938951805,"args":{"Destinations":[1],"Location":"Origin","Origin":0,"mpi_tag":27}},{"ph":"X","name":"Submit","pid":24294,"tid":24412,"ts":2221393.225997925,"dur":181.60000213608146,"args":{"Destinations":[1],"Location":"Origin","Origin":0,"mpi_tag":28}},{"ph":"X","name":"Execute","pid":24294,"tid":24412,"ts":2221659.6159973145,"dur":2892826.2560006715,"args":{"Destinations":[1],"Location":"Origin","Origin":0,"mpi_tag":29,"task_id":491}},{"ph":"X","name":"Retrieve","pid":24294,"tid":24412,"ts":5114731.722000122,"dur":330.33999572787434,"args":{"Destinations":[1],"Location":"Origin","Origin":0,"mpi_tag":30}},{"name":"edge","cat":"Tasks Dependencies","args":{},"id":"V490V49119640","pid":24294,"tid":24412,"ph":"f","bp":"e","ts":2221659.6159973145},{"name":"edge","cat":"Tasks Dependencies","args":{},"id":"V490V49119640","pid":24294,"tid":24412,"ph":"s","ts":2219712.764573584},{"name":"edge","cat":"Tasks Dependencies","args":{},"id":"V488V48919640","pid":24294,"tid":24409,"ph":"f","bp":"e","ts":1516639.8549957275},{"name":"edge","cat":"Tasks Dependencies","args":{},"id":"V488V48919640","pid":24294,"tid":24409,"ph":"s","ts":1514357.848380476},{"name":"edge","cat":"Tasks Dependencies","args":{},"id":"V486V48719640","pid":24294,"tid":24411,"ph":"f","bp":"e","ts":3011777.7799987793},{"name":"edge","cat":"Tasks Dependencies","args":{},"id":"V486V48719640","pid":24294,"tid":24411,"ph":"s","ts":3010445.6879628515},{"name":"edge","cat":"Tasks Dependencies","args":{},"id":"V484V48519640","pid":24294,"tid":24413,"ph":"f","bp":"e","ts":915436.5069961548},{"name":"edge","cat":"Tasks Dependencies","args":{},"id":"V484V48519640","pid":24294,"tid":24413,"ph":"s","ts":815353.3542572714},{"name":"edge","cat":"Worker Process 0","args":{},"id":"84394","pid":24294,"tid":24413,"ph":"s","ts":75612.34199523926},{"name":"edge","cat":"Worker Process 0","args":{},"id":"84394","pid":2352,"tid":2355,"ph":"f","bp":"e","ts":75671.88199615479},{"name":"edge","cat":"Worker Process 0","args":{},"id":"36075","pid":2352,"tid":2355,"ph":"s","ts":815056.2046110928},{"name":"edge","cat":"Worker Process 0","args":{},"id":"36075","pid":24294,"tid":24413,"ph":"f","bp":"e","ts":815353.3542572714},{"name":"edge","cat":"Worker Process 0","args":{},"id":"35405","pid":24294,"tid":24409,"ph":"s","ts":77741.59199523926},{"name":"edge","cat":"Worker Process 0","args":{},"id":"35405","pid":2352,"tid":2355,"ph":"f","bp":"e","ts":815236.2539978027},{"name":"edge","cat":"Worker Process 0","args":{},"id":"69645","pid":2352,"tid":2355,"ph":"s","ts":1511873.978359382},{"name":"edge","cat":"Worker Process 0","args":{},"id":"69645","pid":24294,"tid":24409,"ph":"f","bp":"e","ts":1514357.848380476},{"name":"edge","cat":"Worker Process 0","args":{},"id":"72544","pid":24294,"tid":24412,"ph":"s","ts":78293.31199645996},{"name":"edge","cat":"Worker Process 0","args":{},"id":"72544","pid":2352,"tid":2355,"ph":"f","bp":"e","ts":1512562.214996338},{"name":"edge","cat":"Worker Process 0","args":{},"id":"68850","pid":2352,"tid":2355,"ph":"s","ts":2219379.889177957},{"name":"edge","cat":"Worker Process 0","args":{},"id":"68850","pid":24294,"tid":24412,"ph":"f","bp":"e","ts":2219712.764573584},{"name":"edge","cat":"Worker Process 0","args":{},"id":"50384","pid":24294,"tid":24411,"ph":"s","ts":78412.08200073242},{"name":"edge","cat":"Worker Process 0","args":{},"id":"50384","pid":2352,"tid":2355,"ph":"f","bp":"e","ts":2219622.6060028076},{"name":"edge","cat":"Worker Process 0","args":{},"id":"94248","pid":2352,"tid":2355,"ph":"s","ts":3010155.3384692846},{"name":"edge","cat":"Worker Process 0","args":{},"id":"94248","pid":24294,"tid":24411,"ph":"f","bp":"e","ts":3010445.6879628515},{"name":"edge","cat":"Worker Process 0","args":{},"id":"02200","pid":24294,"tid":24413,"ph":"s","ts":915436.5069961548},{"name":"edge","cat":"Worker Process 0","args":{},"id":"02200","pid":2352,"tid":2355,"ph":"f","bp":"e","ts":3010351.839996338},{"name":"edge","cat":"Worker Process 0","args":{},"id":"51028","pid":2352,"tid":2355,"ph":"s","ts":3711435.048912428},{"name":"edge","cat":"Worker Process 0","args":{},"id":"51028","pid":24294,"tid":24413,"ph":"f","bp":"e","ts":3711734.673698121},{"name":"edge","cat":"Worker Process 0","args":{},"id":"81234","pid":24294,"tid":24409,"ph":"s","ts":1516639.8549957275},{"name":"edge","cat":"Worker Process 0","args":{},"id":"81234","pid":2352,"tid":2355,"ph":"f","bp":"e","ts":3711611.769996643},{"name":"edge","cat":"Worker Process 0","args":{},"id":"03525","pid":2352,"tid":2355,"ph":"s","ts":4410118.252489462},{"name":"edge","cat":"Worker Process 0","args":{},"id":"03525","pid":24294,"tid":24409,"ph":"f","bp":"e","ts":4410802.546833865},{"name":"edge","cat":"Worker Process 0","args":{},"id":"81689","pid":24294,"tid":24412,"ph":"s","ts":2221659.6159973145},{"name":"edge","cat":"Worker Process 0","args":{},"id":"81689","pid":2352,"tid":2355,"ph":"f","bp":"e","ts":4410400.691001892},{"name":"edge","cat":"Worker Process 0","args":{},"id":"26589","pid":2352,"tid":2355,"ph":"s","ts":5114116.558285321},{"name":"edge","cat":"Worker Process 0","args":{},"id":"26589","pid":24294,"tid":24412,"ph":"f","bp":"e","ts":5114482.97917173},{"name":"edge","cat":"Worker Process 0","args":{},"id":"33345","pid":24294,"tid":24411,"ph":"s","ts":3011777.7799987793},{"name":"edge","cat":"Worker Process 0","args":{},"id":"33345","pid":2352,"tid":2355,"ph":"f","bp":"e","ts":5114310.592002869},{"name":"edge","cat":"Worker Process 0","args":{},"id":"44076","pid":2352,"tid":2355,"ph":"s","ts":5818115.899196858},{"name":"edge","cat":"Worker Process 0","args":{},"id":"44076","pid":24294,"tid":24411,"ph":"f","bp":"e","ts":5822334.34244081},{"name":"edge","cat":"Communication","args":{},"id":"56634","pid":2352,"tid":2356,"ph":"s","ts":74229.25199888655},{"name":"edge","cat":"Communication","args":{},"id":"56634","pid":2352,"tid":2356,"ph":"f","bp":"e","ts":74407.85199737549},{"name":"edge","cat":"Communication","args":{},"id":"33648","pid":2352,"tid":2356,"ph":"s","ts":74670.9319984862},{"name":"edge","cat":"Communication","args":{},"id":"33648","pid":2352,"tid":2356,"ph":"f","bp":"e","ts":74806.71199798584},{"name":"edge","cat":"Communication","args":{},"id":"15909","pid":2352,"tid":2356,"ph":"s","ts":74993.14199637996},{"name":"edge","cat":"Communication","args":{},"id":"15909","pid":2352,"tid":2356,"ph":"f","bp":"e","ts":75100.82199859619},{"name":"edge","cat":"Communication","args":{},"id":"11880","pid":2352,"tid":2356,"ph":"s","ts":75278.22199606478},{"name":"edge","cat":"Communication","args":{},"id":"11880","pid":2352,"tid":2356,"ph":"f","bp":"e","ts":75388.70199584961},{"name":"edge","cat":"Communication","args":{},"id":"24105","pid":2352,"tid":2356,"ph":"s","ts":76244.89199637996},{"name":"edge","cat":"Communication","args":{},"id":"24105","pid":2352,"tid":2356,"ph":"f","bp":"e","ts":76977.68199920654},{"name":"edge","cat":"Communication","args":{},"id":"61953","pid":2352,"tid":2356,"ph":"s","ts":77134.48200249349},{"name":"edge","cat":"Communication","args":{},"id":"61953","pid":2352,"tid":2356,"ph":"f","bp":"e","ts":77230.38199615479},{"name":"edge","cat":"Communication","args":{},"id":"85657","pid":2352,"tid":2356,"ph":"s","ts":77386.05200218831},{"name":"edge","cat":"Communication","args":{},"id":"85657","pid":2352,"tid":2356,"ph":"f","bp":"e","ts":77519.21199798584},{"name":"edge","cat":"Communication","args":{},"id":"48399","pid":2352,"tid":2356,"ph":"s","ts":77881.44199943171},{"name":"edge","cat":"Communication","args":{},"id":"48399","pid":2352,"tid":2356,"ph":"f","bp":"e","ts":77990.27200317383},{"name":"edge","cat":"Communication","args":{},"id":"45097","pid":2352,"tid":2356,"ph":"s","ts":78009.80200218831},{"name":"edge","cat":"Communication","args":{},"id":"45097","pid":2352,"tid":2356,"ph":"f","bp":"e","ts":78080.19200134277},{"name":"edge","cat":"Communication","args":{},"id":"97795","pid":2352,"tid":2356,"ph":"s","ts":818348.6740002494},{"name":"edge","cat":"Communication","args":{},"id":"97795","pid":2352,"tid":2356,"ph":"f","bp":"e","ts":818529.4039993286},{"name":"edge","cat":"Communication","args":{},"id":"61370","pid":2352,"tid":2356,"ph":"s","ts":819087.5439968072},{"name":"edge","cat":"Communication","args":{},"id":"61370","pid":2352,"tid":2356,"ph":"f","bp":"e","ts":819217.4339981079},{"name":"edge","cat":"Communication","args":{},"id":"30434","pid":2352,"tid":2356,"ph":"s","ts":819380.4240028807},{"name":"edge","cat":"Communication","args":{},"id":"30434","pid":2352,"tid":2356,"ph":"f","bp":"e","ts":819482.1640014648},{"name":"edge","cat":"Communication","args":{},"id":"77318","pid":2352,"tid":2356,"ph":"s","ts":910166.2769963699},{"name":"edge","cat":"Communication","args":{},"id":"77318","pid":2352,"tid":2356,"ph":"f","bp":"e","ts":910321.5670013428},{"name":"edge","cat":"Communication","args":{},"id":"59220","pid":2352,"tid":2356,"ph":"s","ts":1514569.685001601},{"name":"edge","cat":"Communication","args":{},"id":"59220","pid":2352,"tid":2356,"ph":"f","bp":"e","ts":1514640.7549972534},{"name":"edge","cat":"Communication","args":{},"id":"98836","pid":2352,"tid":2356,"ph":"s","ts":1515602.8650014359},{"name":"edge","cat":"Communication","args":{},"id":"98836","pid":2352,"tid":2356,"ph":"f","bp":"e","ts":1515702.5349960327},{"name":"edge","cat":"Communication","args":{},"id":"11559","pid":2352,"tid":2356,"ph":"s","ts":1516168.0349962679},{"name":"edge","cat":"Communication","args":{},"id":"11559","pid":2352,"tid":2356,"ph":"f","bp":"e","ts":1516233.2849960327},{"name":"edge","cat":"Communication","args":{},"id":"38118","pid":2352,"tid":2356,"ph":"s","ts":2219849.4760002913},{"name":"edge","cat":"Communication","args":{},"id":"38118","pid":2352,"tid":2356,"ph":"f","bp":"e","ts":2219995.1259994507},{"name":"edge","cat":"Communication","args":{},"id":"42430","pid":2352,"tid":2356,"ph":"s","ts":2220990.396001812},{"name":"edge","cat":"Communication","args":{},"id":"42430","pid":2352,"tid":2356,"ph":"f","bp":"e","ts":2221065.3959960938},{"name":"edge","cat":"Communication","args":{},"id":"37936","pid":2352,"tid":2356,"ph":"s","ts":2221345.3459987603},{"name":"edge","cat":"Communication","args":{},"id":"37936","pid":2352,"tid":2356,"ph":"f","bp":"e","ts":2221409.3759994507},{"name":"edge","cat":"Communication","args":{},"id":"94946","pid":2352,"tid":2356,"ph":"s","ts":3010621.4999952074},{"name":"edge","cat":"Communication","args":{},"id":"94946","pid":2352,"tid":2356,"ph":"f","bp":"e","ts":3010728.180000305},{"name":"edge","cat":"Communication","args":{},"id":"35694","pid":2352,"tid":2356,"ph":"s","ts":3011462.1599974586},{"name":"edge","cat":"Communication","args":{},"id":"35694","pid":2352,"tid":2356,"ph":"f","bp":"e","ts":3011572.1100006104},{"name":"edge","cat":"Communication","args":{},"id":"63941","pid":2352,"tid":2356,"ph":"s","ts":3810656.864000137},{"name":"edge","cat":"Communication","args":{},"id":"63941","pid":2352,"tid":2356,"ph":"f","bp":"e","ts":3810799.053001404},{"name":"edge","cat":"Communication","args":{},"id":"10968","pid":2352,"tid":2356,"ph":"s","ts":4410999.861001957},{"name":"edge","cat":"Communication","args":{},"id":"10968","pid":2352,"tid":2356,"ph":"f","bp":"e","ts":4411136.411003113},{"name":"edge","cat":"Communication","args":{},"id":"39090","pid":2352,"tid":2356,"ph":"s","ts":5114776.831997146},{"name":"edge","cat":"Communication","args":{},"id":"39090","pid":2352,"tid":2356,"ph":"f","bp":"e","ts":5114841.781997681},{"name":"edge","cat":"Communication","args":{},"id":"60483","pid":2352,"tid":2356,"ph":"s","ts":5822476.322996356},{"name":"edge","cat":"Communication","args":{},"id":"60483","pid":2352,"tid":2356,"ph":"f","bp":"e","ts":5822628.602996826},{"name":"edge","cat":"Communication","args":{},"id":"95259","pid":2352,"tid":2356,"ph":"s","ts":5910146.656002993},{"name":"edge","cat":"Communication","args":{},"id":"95259","pid":2352,"tid":2356,"ph":"f","bp":"e","ts":5910352.236000061},{"ph":"X","name":"Alloc / Begin","pid":2352,"tid":2356,"ts":74228.93199920654,"dur":0.32,"args":{"Destinations":[1],"Location":"Destination","Origin":0,"mpi_tag":1}},{"ph":"X","name":"Submit / Begin","pid":2352,"tid":2356,"ts":74670.82199859619,"dur":0.11,"args":{"Destinations":[1],"Location":"Destination","Origin":0,"mpi_tag":2}},{"ph":"X","name":"Submit / Begin","pid":2352,"tid":2356,"ts":74993.06199645996,"dur":0.08,"args":{"Destinations":[1],"Location":"Destination","Origin":0,"mpi_tag":3}},{"ph":"X","name":"Submit / Begin","pid":2352,"tid":2356,"ts":75278.13199615479,"dur":0.09,"args":{"Destinations":[1],"Location":"Destination","Origin":0,"mpi_tag":4}},{"ph":"X","name":"Submit / Begin","pid":2352,"tid":2356,"ts":76244.81199645996,"dur":0.08,"args":{"Destinations":[1],"Location":"Destination","Origin":0,"mpi_tag":7}},{"ph":"X","name":"Submit / Begin","pid":2352,"tid":2356,"ts":77134.41200256348,"dur":0.07,"args":{"Destinations":[1],"Location":"Destination","Origin":0,"mpi_tag":8}},{"ph":"X","name":"Submit / Begin","pid":2352,"tid":2356,"ts":77385.9820022583,"dur":0.07,"args":{"Destinations":[1],"Location":"Destination","Origin":0,"mpi_tag":11}},{"ph":"X","name":"Submit / Begin","pid":2352,"tid":2356,"ts":77881.36199951172,"dur":0.08,"args":{"Destinations":[1],"Location":"Destination","Origin":0,"mpi_tag":15}},{"ph":"X","name":"Submit / Begin","pid":2352,"tid":2356,"ts":78009.7320022583,"dur":0.07,"args":{"Destinations":[1],"Location":"Destination","Origin":0,"mpi_tag":12}},{"ph":"X","name":"Retrieve / Begin","pid":2352,"tid":2356,"ts":818348.3740005493,"dur":0.3,"args":{"Destinations":[1],"Location":"Destination","Origin":0,"mpi_tag":6}},{"ph":"X","name":"Submit / Begin","pid":2352,"tid":2356,"ts":819087.4639968872,"dur":0.08,"args":{"Destinations":[1],"Location":"Destination","Origin":0,"mpi_tag":18}},{"ph":"X","name":"Submit / Begin","pid":2352,"tid":2356,"ts":819380.3140029907,"dur":0.11,"args":{"Destinations":[1],"Location":"Destination","Origin":0,"mpi_tag":19}},{"ph":"X","name":"Submit / Begin","pid":2352,"tid":2356,"ts":910166.18699646,"dur":0.09,"args":{"Destinations":[1],"Location":"Destination","Origin":0,"mpi_tag":20}},{"ph":"X","name":"Retrieve / Begin","pid":2352,"tid":2356,"ts":1514569.455001831,"dur":0.23,"args":{"Destinations":[1],"Location":"Destination","Origin":0,"mpi_tag":10}},{"ph":"X","name":"Submit / Begin","pid":2352,"tid":2356,"ts":1515602.7750015259,"dur":0.09,"args":{"Destinations":[1],"Location":"Destination","Origin":0,"mpi_tag":23}},{"ph":"X","name":"Submit / Begin","pid":2352,"tid":2356,"ts":1516167.964996338,"dur":0.07,"args":{"Destinations":[1],"Location":"Destination","Origin":0,"mpi_tag":24}},{"ph":"X","name":"Retrieve / Begin","pid":2352,"tid":2356,"ts":2219849.0960006714,"dur":0.38,"args":{"Destinations":[1],"Location":"Destination","Origin":0,"mpi_tag":17}},{"ph":"X","name":"Submit / Begin","pid":2352,"tid":2356,"ts":2220990.316001892,"dur":0.08,"args":{"Destinations":[1],"Location":"Destination","Origin":0,"mpi_tag":27}},{"ph":"X","name":"Submit / Begin","pid":2352,"tid":2356,"ts":2221345.2659988403,"dur":0.08,"args":{"Destinations":[1],"Location":"Destination","Origin":0,"mpi_tag":28}},{"ph":"X","name":"Retrieve / Begin","pid":2352,"tid":2356,"ts":3010620.9799957275,"dur":0.52,"args":{"Destinations":[1],"Location":"Destination","Origin":0,"mpi_tag":14}},{"ph":"X","name":"Submit / Begin","pid":2352,"tid":2356,"ts":3011462.0599975586,"dur":0.1,"args":{"Destinations":[1],"Location":"Destination","Origin":0,"mpi_tag":31}},{"ph":"X","name":"Retrieve / Begin","pid":2352,"tid":2356,"ts":3810656.5130004883,"dur":0.351,"args":{"Destinations":[1],"Location":"Destination","Origin":0,"mpi_tag":22}},{"ph":"X","name":"Retrieve / Begin","pid":2352,"tid":2356,"ts":4410999.621002197,"dur":0.24,"args":{"Destinations":[1],"Location":"Destination","Origin":0,"mpi_tag":26}},{"ph":"X","name":"Retrieve / Begin","pid":2352,"tid":2356,"ts":5114776.6019973755,"dur":0.23,"args":{"Destinations":[1],"Location":"Destination","Origin":0,"mpi_tag":30}},{"ph":"X","name":"Retrieve / Begin","pid":2352,"tid":2356,"ts":5822475.852996826,"dur":0.47,"args":{"Destinations":[1],"Location":"Destination","Origin":0,"mpi_tag":33}},{"ph":"X","name":"Delete / Begin","pid":2352,"tid":2356,"ts":5910146.536003113,"dur":0.12,"args":{"Destinations":[1],"Location":"Destination","Origin":0,"mpi_tag":34}},{"ph":"X","name":"Alloc / End","pid":2352,"tid":2356,"ts":74407.85199737549,"dur":0.11,"args":{"Destinations":[1],"Location":"Destination","Origin":0,"mpi_tag":1}},{"ph":"X","name":"Submit / End","pid":2352,"tid":2356,"ts":74806.71199798584,"dur":0.09,"args":{"Destinations":[1],"Location":"Destination","Origin":0,"mpi_tag":2}},{"ph":"X","name":"Submit / End","pid":2352,"tid":2356,"ts":75100.82199859619,"dur":0.08,"args":{"Destinations":[1],"Location":"Destination","Origin":0,"mpi_tag":3}},{"ph":"X","name":"Submit / End","pid":2352,"tid":2356,"ts":75388.70199584961,"dur":0.07,"args":{"Destinations":[1],"Location":"Destination","Origin":0,"mpi_tag":4}},{"ph":"X","name":"Submit / End","pid":2352,"tid":2356,"ts":76977.68199920654,"dur":0.12,"args":{"Destinations":[1],"Location":"Destination","Origin":0,"mpi_tag":7}},{"ph":"X","name":"Submit / End","pid":2352,"tid":2356,"ts":77230.38199615479,"dur":0.06,"args":{"Destinations":[1],"Location":"Destination","Origin":0,"mpi_tag":8}},{"ph":"X","name":"Submit / End","pid":2352,"tid":2356,"ts":77519.21199798584,"dur":0.09,"args":{"Destinations":[1],"Location":"Destination","Origin":0,"mpi_tag":11}},{"ph":"X","name":"Submit / End","pid":2352,"tid":2356,"ts":77990.27200317383,"dur":0.09,"args":{"Destinations":[1],"Location":"Destination","Origin":0,"mpi_tag":15}},{"ph":"X","name":"Submit / End","pid":2352,"tid":2356,"ts":78080.19200134277,"dur":0.07,"args":{"Destinations":[1],"Location":"Destination","Origin":0,"mpi_tag":12}},{"ph":"X","name":"Retrieve / End","pid":2352,"tid":2356,"ts":818529.4039993286,"dur":0.11,"args":{"Destinations":[1],"Location":"Destination","Origin":0,"mpi_tag":6}},{"ph":"X","name":"Submit / End","pid":2352,"tid":2356,"ts":819217.4339981079,"dur":0.09,"args":{"Destinations":[1],"Location":"Destination","Origin":0,"mpi_tag":18}},{"ph":"X","name":"Submit / End","pid":2352,"tid":2356,"ts":819482.1640014648,"dur":0.14,"args":{"Destinations":[1],"Location":"Destination","Origin":0,"mpi_tag":19}},{"ph":"X","name":"Submit / End","pid":2352,"tid":2356,"ts":910321.5670013428,"dur":0.31,"args":{"Destinations":[1],"Location":"Destination","Origin":0,"mpi_tag":20}},{"ph":"X","name":"Retrieve / End","pid":2352,"tid":2356,"ts":1514640.7549972534,"dur":0.12,"args":{"Destinations":[1],"Location":"Destination","Origin":0,"mpi_tag":10}},{"ph":"X","name":"Submit / End","pid":2352,"tid":2356,"ts":1515702.5349960327,"dur":0.08,"args":{"Destinations":[1],"Location":"Destination","Origin":0,"mpi_tag":23}},{"ph":"X","name":"Submit / End","pid":2352,"tid":2356,"ts":1516233.2849960327,"dur":0.1,"args":{"Destinations":[1],"Location":"Destination","Origin":0,"mpi_tag":24}},{"ph":"X","name":"Retrieve / End","pid":2352,"tid":2356,"ts":2219995.1259994507,"dur":0.35,"args":{"Destinations":[1],"Location":"Destination","Origin":0,"mpi_tag":17}},{"ph":"X","name":"Submit / End","pid":2352,"tid":2356,"ts":2221065.3959960938,"dur":0.09,"args":{"Destinations":[1],"Location":"Destination","Origin":0,"mpi_tag":27}},{"ph":"X","name":"Submit / End","pid":2352,"tid":2356,"ts":2221409.3759994507,"dur":0.07,"args":{"Destinations":[1],"Location":"Destination","Origin":0,"mpi_tag":28}},{"ph":"X","name":"Retrieve / End","pid":2352,"tid":2356,"ts":3010728.180000305,"dur":0.08,"args":{"Destinations":[1],"Location":"Destination","Origin":0,"mpi_tag":14}},{"ph":"X","name":"Submit / End","pid":2352,"tid":2356,"ts":3011572.1100006104,"dur":0.11,"args":{"Destinations":[1],"Location":"Destination","Origin":0,"mpi_tag":31}},{"ph":"X","name":"Retrieve / End","pid":2352,"tid":2356,"ts":3810799.053001404,"dur":0.08,"args":{"Destinations":[1],"Location":"Destination","Origin":0,"mpi_tag":22}},{"ph":"X","name":"Retrieve / End","pid":2352,"tid":2356,"ts":4411136.411003113,"dur":0.11,"args":{"Destinations":[1],"Location":"Destination","Origin":0,"mpi_tag":26}},{"ph":"X","name":"Retrieve / End","pid":2352,"tid":2356,"ts":5114841.781997681,"dur":0.1,"args":{"Destinations":[1],"Location":"Destination","Origin":0,"mpi_tag":30}},{"ph":"X","name":"Retrieve / End","pid":2352,"tid":2356,"ts":5822628.602996826,"dur":0.08,"args":{"Destinations":[1],"Location":"Destination","Origin":0,"mpi_tag":33}},{"ph":"X","name":"Delete / End","pid":2352,"tid":2356,"ts":5910352.236000061,"dur":0.28,"args":{"Destinations":[1],"Location":"Destination","Origin":0,"mpi_tag":34}}]}